[
  {
    "a_date_farmed": "16/07/2024",
    "b_source": "10Times",
    "c_scraped_url": "https://10times.com/e1xs-x2h9-z5f9",
    "d": "New Lead",
    "e": "Opportunity",
    "f": "Juan",
    "g": "Juan",
    "h": "Lara",
    "i": "Scraping",
    "j": "EDU Business",
    "k": "EDU Events",
    "l": "",
    "m_date_of_event": "Thu, 25 - Sat, 27 Jul 2024",
    "n_event_name": "World Conference on Education and Training",
    "o_description": "The World Conference on Education and Training (WCET) is a hybrid event happening in Singapore. It will include breakout sessions, poster exhibitions, and discussions on education topics. Attendees will be educators, researchers, administrators, etc. Singapore's renowned education system provides a dynamic setting for the conference, which will cover sciences education, teacher education, management education, and more.",
    "p": "",
    "q": "",
    "r": "",
    "s_state_province": "\n                    InterContinental,  SingaporeGet Directions",
    "t": "Singapore",
    "u": "Southeast Asia",
    "v": "",
    "w": "",
    "x": "",
    "y": "",
    "z": "",
    "aa": "",
    "ab_business_info": "",
    "ac_website": "",
    "ad": "",
    "ae": "",
    "af_country": "",
    "ag": "",
    "company_url": ""
  },
  {
    "a_date_farmed": "16/07/2024",
    "b_source": "10Times",
    "c_scraped_url": "https://10times.com/ictel-singapore",
    "d": "New Lead",
    "e": "Opportunity",
    "f": "Juan",
    "g": "Juan",
    "h": "Lara",
    "i": "Scraping",
    "j": "EDU Business",
    "k": "EDU Events",
    "l": "",
    "m_date_of_event": "Mon, 03 - Tue, 04 Mar 2025",
    "n_event_name": "International Conference on Teaching, Education & Learning (ICTEL)",
    "o_description": "\"Collaborate to co-create\"The event focuses on challenges of higher education in a post-pandemic world, featuring a professor with expertise in systems engineering, e-learning, and educational sciences. The event will cover topics such as literature, power, ideology, and interdisciplinary possibilities in literary studies.",
    "p": "",
    "q": "",
    "r": "",
    "s_state_province": "\n                    Kent Ridge Guild House,  SingaporeGet Directions",
    "t": "Singapore",
    "u": "Southeast Asia",
    "v": "",
    "w": "",
    "x": "",
    "y": "",
    "z": "",
    "aa": "",
    "ab_business_info": "Eurasia Research",
    "ac_website": "https://eurasiaresearch.org/",
    "ad": "",
    "ae": "",
    "af_country": "India",
    "ag": "",
    "company_url": "https://10times.com/company/protobex-asia-expo"
  },
  {
    "a_date_farmed": "16/07/2024",
    "b_source": "10Times",
    "c_scraped_url": "",
    "d": "New Lead",
    "e": "Opportunity",
    "f": "Juan",
    "g": "Juan",
    "h": "Lara",
    "i": "Scraping",
    "j": "EDU Business",
    "k": "EDU Events",
    "l": "",
    "m_date_of_event": "",
    "n_event_name": "",
    "o_description": "",
    "p": "",
    "q": "",
    "r": "",
    "s_state_province": "",
    "t": "Singapore",
    "u": "Southeast Asia",
    "v": "",
    "w": "",
    "x": "",
    "y": "",
    "z": "",
    "aa": "",
    "ab_business_info": "",
    "ac_website": "",
    "ad": "",
    "ae": "",
    "af_country": "",
    "ag": ""
  },
  {
    "a_date_farmed": "16/07/2024",
    "b_source": "10Times",
    "c_scraped_url": "https://10times.com/e15x-rd4d-gd42",
    "d": "New Lead",
    "e": "Opportunity",
    "f": "Juan",
    "g": "Juan",
    "h": "Lara",
    "i": "Scraping",
    "j": "EDU Business",
    "k": "EDU Events",
    "l": "",
    "m_date_of_event": "Sun, 04 Aug 2024",
    "n_event_name": "International Conference on Teaching, Education and New Learning Technologies (ICTENLT)",
    "o_description": "The ARSSS - ICTENLT International conference on Teaching, Education, and new Learning Technologies provides a platform for researchers, academicians, and students to share their findings with global experts. Best paper awards are given for significant contributions.",
    "p": "",
    "q": "",
    "r": "",
    "s_state_province": "Singapore",
    "t": "Singapore",
    "u": "Southeast Asia",
    "v": "",
    "w": "",
    "x": "",
    "y": "",
    "z": "",
    "aa": "",
    "ab_business_info": "Advanced Research Society for Science and Sociology",
    "ac_website": "",
    "ad": "",
    "ae": "",
    "af_country": "",
    "ag": "",
    "company_url": "https://10times.com/company/advanced-research-society-for-science-and-sociology"
  },
  {
    "a_date_farmed": "16/07/2024",
    "b_source": "10Times",
    "c_scraped_url": "",
    "d": "New Lead",
    "e": "Opportunity",
    "f": "Juan",
    "g": "Juan",
    "h": "Lara",
    "i": "Scraping",
    "j": "EDU Business",
    "k": "EDU Events",
    "l": "",
    "m_date_of_event": "",
    "n_event_name": "",
    "o_description": "",
    "p": "",
    "q": "",
    "r": "",
    "s_state_province": "",
    "t": "Singapore",
    "u": "Southeast Asia",
    "v": "",
    "w": "",
    "x": "",
    "y": "",
    "z": "",
    "aa": "",
    "ab_business_info": "",
    "ac_website": "",
    "ad": "",
    "ae": "",
    "af_country": "",
    "ag": ""
  },
  {
    "a_date_farmed": "16/07/2024",
    "b_source": "10Times",
    "c_scraped_url": "https://10times.com/world-mba-tour",
    "d": "New Lead",
    "e": "Opportunity",
    "f": "Juan",
    "g": "Juan",
    "h": "Lara",
    "i": "Scraping",
    "j": "EDU Business",
    "k": "EDU Events",
    "l": "",
    "m_date_of_event": "Sat, 17 Aug 2024",
    "n_event_name": "Singapore's MBA Fair",
    "o_description": "All Events in Singapore",
    "p": "",
    "q": "",
    "r": "",
    "s_state_province": "\n                    Marina Bay Sands Expo,  SingaporeGet Directions",
    "t": "Singapore",
    "u": "Southeast Asia",
    "v": "",
    "w": "",
    "x": "",
    "y": "",
    "z": "",
    "aa": "",
    "ab_business_info": "QS Quacquarelli Symonds Limited",
    "ac_website": "http://www.qs.com",
    "ad": "",
    "ae": "",
    "af_country": "UK",
    "ag": "",
    "company_url": "https://10times.com/company/quacquarelli-symonds-ltd-qs"
  },
  {
    "a_date_farmed": "16/07/2024",
    "b_source": "10Times",
    "c_scraped_url": "https://10times.com/e1rf-fz3h-3x47",
    "d": "New Lead",
    "e": "Opportunity",
    "f": "Juan",
    "g": "Juan",
    "h": "Lara",
    "i": "Scraping",
    "j": "EDU Business",
    "k": "EDU Events",
    "l": "",
    "m_date_of_event": "Sun, 21 - Mon, 22 Jul 2024",
    "n_event_name": "International Conference on Medical, Medicine and Health Sciences (ICMMH)",
    "o_description": "\"Conference will cover vital issues in medical, medicine and health sciences under multiplesub-themes\"ICMMH is a premier interdisciplinary forum covering vital issues in medical, medicine, and health sciences. Aim to support networking, sharing, publishing, and nurturing growth of scholars globally. Discuss innovations in the field with researchers, practitioners, and educators.",
    "p": "",
    "q": "",
    "r": "",
    "s_state_province": "\n                    Village Hotel Changi,  SingaporeGet Directions",
    "t": "Singapore",
    "u": "Southeast Asia",
    "v": "",
    "w": "",
    "x": "",
    "y": "",
    "z": "",
    "aa": "",
    "ab_business_info": "International Institute Of Engineers Researchers & Doctors",
    "ac_website": "http://www.iierd.com/",
    "ad": "",
    "ae": "",
    "af_country": "India",
    "ag": "",
    "company_url": "https://10times.com/company/international-institute-of-engineers-researchers-doctors"
  },
  {
    "a_date_farmed": "16/07/2024",
    "b_source": "10Times",
    "c_scraped_url": "https://10times.com/edutech-asia",
    "d": "New Lead",
    "e": "Opportunity",
    "f": "Juan",
    "g": "Juan",
    "h": "Lara",
    "i": "Scraping",
    "j": "EDU Business",
    "k": "EDU Events",
    "l": "",
    "m_date_of_event": "Wed, 06 - Thu, 07 Nov 2024",
    "n_event_name": "EduTech Asia",
    "o_description": "EduTech Asia is not just about speeches and presentations; it's about dialogue and collaboration. It's about forging connections and partnerships that will drive meaningful change in education. It's about sharing insights and experiences that will inspire and empower all educators to be the change-makers the sector needs.",
    "p": "",
    "q": "",
    "r": "",
    "s_state_province": "\n                    Sands Expo and Convention Centre,  SingaporeGet Directions",
    "t": "Singapore",
    "u": "Southeast Asia",
    "v": "",
    "w": "",
    "x": "",
    "y": "",
    "z": "",
    "aa": "",
    "ab_business_info": "Terrapinn Holdings Ltd.",
    "ac_website": "http://www.terrapinn.com",
    "ad": "",
    "ae": "",
    "af_country": "UK",
    "ag": "",
    "company_url": "https://10times.com/company/terrapinn-pte"
  },
  {
    "a_date_farmed": "16/07/2024",
    "b_source": "10Times",
    "c_scraped_url": "https://10times.com/icbef-singapore",
    "d": "New Lead",
    "e": "Opportunity",
    "f": "Juan",
    "g": "Juan",
    "h": "Lara",
    "i": "Scraping",
    "j": "EDU Business",
    "k": "EDU Events",
    "l": "",
    "m_date_of_event": "Thu, 08 - Fri, 09 Aug 2024",
    "n_event_name": "International Conference on Business Economics and Finance (ICBEF)",
    "o_description": "ICBEF conference for researchers, scholars, and students to share knowledge in technology application. Promotes scientific and educational activities in engineering with publication opportunities and recognition through awards and exchange programs.",
    "p": "",
    "q": "",
    "r": "",
    "s_state_province": "\n                    Village Hotel Changi,  SingaporeGet Directions",
    "t": "Singapore",
    "u": "Southeast Asia",
    "v": "",
    "w": "",
    "x": "",
    "y": "",
    "z": "",
    "aa": "",
    "ab_business_info": "TECHNOARETE INTERNATIONAL",
    "ac_website": "",
    "ad": "",
    "ae": "",
    "af_country": "",
    "ag": "",
    "company_url": "https://10times.com/company/technoarete"
  },
  {
    "a_date_farmed": "16/07/2024",
    "b_source": "10Times",
    "c_scraped_url": "https://10times.com/icsstl",
    "d": "New Lead",
    "e": "Opportunity",
    "f": "Juan",
    "g": "Juan",
    "h": "Lara",
    "i": "Scraping",
    "j": "EDU Business",
    "k": "EDU Events",
    "l": "",
    "m_date_of_event": "Mon, 29 - Tue, 30 Jul 2024",
    "n_event_name": "International Conference on Social Science, Teaching and Learning (ICSSTL)",
    "o_description": "",
    "p": "",
    "q": "",
    "r": "",
    "s_state_province": "Singapore  •  Virtual Event",
    "t": "Singapore",
    "u": "Southeast Asia",
    "v": "",
    "w": "",
    "x": "",
    "y": "",
    "z": "",
    "aa": "",
    "ab_business_info": "",
    "ac_website": "",
    "ad": "",
    "ae": "",
    "af_country": "",
    "ag": "",
    "company_url": ""
  },
  {
    "a_date_farmed": "16/07/2024",
    "b_source": "10Times",
    "c_scraped_url": "https://10times.com/british-boarding-schools-show-singapore",
    "d": "New Lead",
    "e": "Opportunity",
    "f": "Juan",
    "g": "Juan",
    "h": "Lara",
    "i": "Scraping",
    "j": "EDU Business",
    "k": "EDU Events",
    "l": "",
    "m_date_of_event": "Sat, 29 Mar 2025",
    "n_event_name": "British Boarding Schools Show",
    "o_description": "",
    "p": "",
    "q": "",
    "r": "",
    "s_state_province": "",
    "t": "Singapore",
    "u": "Southeast Asia",
    "v": "",
    "w": "",
    "x": "",
    "y": "",
    "z": "",
    "aa": "",
    "ab_business_info": "",
    "ac_website": "",
    "ad": "",
    "ae": "",
    "af_country": "",
    "ag": "",
    "company_url": ""
  },
  {
    "a_date_farmed": "16/07/2024",
    "b_source": "10Times",
    "c_scraped_url": "https://10times.com/caa-international-cocoa-conference",
    "d": "New Lead",
    "e": "Opportunity",
    "f": "Juan",
    "g": "Juan",
    "h": "Lara",
    "i": "Scraping",
    "j": "EDU Business",
    "k": "EDU Events",
    "l": "",
    "m_date_of_event": "Thu, 12 - Fri, 13 Sep 2024",
    "n_event_name": "CAA International Cocoa Conference",
    "o_description": "The Cocoa Association of Asia organized a 2-day physical cocoa event in Singapore with over 500 world-leading players from across the value chain. The conference aimed to reconnect, discuss, and network, with attendees from 60+ countries. The organizer's current role involves educating cocoa farmers on sustainable practices, promoting gender-based issues, and ensuring a balance in sustainable development. They hold an MBA from ESADE Business School and a BA in International Relations and French from San Francisco State University.",
    "p": "",
    "q": "",
    "r": "",
    "s_state_province": "\n                    Raffles City Convention Centre,  SingaporeGet Directions",
    "t": "Singapore",
    "u": "Southeast Asia",
    "v": "",
    "w": "",
    "x": "",
    "y": "",
    "z": "",
    "aa": "",
    "ab_business_info": "",
    "ac_website": "",
    "ad": "",
    "ae": "",
    "af_country": "",
    "ag": "",
    "company_url": ""
  },
  {
    "a_date_farmed": "16/07/2024",
    "b_source": "10Times",
    "c_scraped_url": "https://10times.com/icem-singapore-conference",
    "d": "New Lead",
    "e": "Opportunity",
    "f": "Juan",
    "g": "Juan",
    "h": "Lara",
    "i": "Scraping",
    "j": "EDU Business",
    "k": "EDU Events",
    "l": "",
    "m_date_of_event": "Wed, 22 - Thu, 23 Jan 2025",
    "n_event_name": "International Conference on Education & Management (ICEM)",
    "o_description": "",
    "p": "",
    "q": "",
    "r": "",
    "s_state_province": "",
    "t": "Singapore",
    "u": "Southeast Asia",
    "v": "",
    "w": "",
    "x": "",
    "y": "",
    "z": "",
    "aa": "",
    "ab_business_info": "",
    "ac_website": "",
    "ad": "",
    "ae": "",
    "af_country": "",
    "ag": "",
    "company_url": ""
  },
  {
    "a_date_farmed": "16/07/2024",
    "b_source": "10Times",
    "c_scraped_url": "https://10times.com/global-security-asia",
    "d": "New Lead",
    "e": "Opportunity",
    "f": "Juan",
    "g": "Juan",
    "h": "Lara",
    "i": "Scraping",
    "j": "EDU Business",
    "k": "EDU Events",
    "l": "",
    "m_date_of_event": "Tue, 28 - Thu, 30 Apr 2026",
    "n_event_name": "Milipol Asia-Pacific",
    "o_description": "Milipol Asia-Pacific is the biggest event in the APAC region that combines an exhibition and conference on internal state security, public safety, and counter-terrorism. Attendees can learn about new technologies, best practices, and network with specialists from around the world. It's ideal for professionals to stay updated on technologies for their continuous education and training.",
    "p": "",
    "q": "",
    "r": "",
    "s_state_province": "\n                    Sands Expo and Convention Centre,  SingaporeGet Directions",
    "t": "Singapore",
    "u": "Southeast Asia",
    "v": "",
    "w": "",
    "x": "",
    "y": "",
    "z": "",
    "aa": "",
    "ab_business_info": "",
    "ac_website": "",
    "ad": "",
    "ae": "",
    "af_country": "",
    "ag": "",
    "company_url": ""
  },
  {
    "a_date_farmed": "16/07/2024",
    "b_source": "10Times",
    "c_scraped_url": "https://10times.com/e1x2-g2hx-5p4x",
    "d": "New Lead",
    "e": "Opportunity",
    "f": "Juan",
    "g": "Juan",
    "h": "Lara",
    "i": "Scraping",
    "j": "EDU Business",
    "k": "EDU Events",
    "l": "",
    "m_date_of_event": "Thu, 22 - Fri, 23 Aug 2024",
    "n_event_name": "International Conference on Future of Education",
    "o_description": "",
    "p": "",
    "q": "",
    "r": "",
    "s_state_province": "",
    "t": "Singapore",
    "u": "Southeast Asia",
    "v": "",
    "w": "",
    "x": "",
    "y": "",
    "z": "",
    "aa": "",
    "ab_business_info": "",
    "ac_website": "",
    "ad": "",
    "ae": "",
    "af_country": "",
    "ag": "",
    "company_url": ""
  },
  {
    "a_date_farmed": "16/07/2024",
    "b_source": "10Times",
    "c_scraped_url": "",
    "d": "New Lead",
    "e": "Opportunity",
    "f": "Juan",
    "g": "Juan",
    "h": "Lara",
    "i": "Scraping",
    "j": "EDU Business",
    "k": "EDU Events",
    "l": "",
    "m_date_of_event": "",
    "n_event_name": "",
    "o_description": "",
    "p": "",
    "q": "",
    "r": "",
    "s_state_province": "",
    "t": "Singapore",
    "u": "Southeast Asia",
    "v": "",
    "w": "",
    "x": "",
    "y": "",
    "z": "",
    "aa": "",
    "ab_business_info": "",
    "ac_website": "",
    "ad": "",
    "ae": "",
    "af_country": "",
    "ag": ""
  },
  {
    "a_date_farmed": "16/07/2024",
    "b_source": "10Times",
    "c_scraped_url": "https://10times.com/e14r-ds1g-s3f4",
    "d": "New Lead",
    "e": "Opportunity",
    "f": "Juan",
    "g": "Juan",
    "h": "Lara",
    "i": "Scraping",
    "j": "EDU Business",
    "k": "EDU Events",
    "l": "",
    "m_date_of_event": "Wed, 28 - Thu, 29 Aug 2024",
    "n_event_name": "The Business Show Asia (TBSA'24)",
    "o_description": "",
    "p": "",
    "q": "",
    "r": "",
    "s_state_province": "Sands Expo and Convention Centre, Singapore",
    "t": "Singapore",
    "u": "Southeast Asia",
    "v": "",
    "w": "",
    "x": "",
    "y": "",
    "z": "",
    "aa": "",
    "ab_business_info": "",
    "ac_website": "",
    "ad": "",
    "ae": "",
    "af_country": "",
    "ag": ""
  },
  {
    "a_date_farmed": "16/07/2024",
    "b_source": "10Times",
    "c_scraped_url": "https://10times.com/humanities-languages-and-social-science",
    "d": "New Lead",
    "e": "Opportunity",
    "f": "Juan",
    "g": "Juan",
    "h": "Lara",
    "i": "Scraping",
    "j": "EDU Business",
    "k": "EDU Events",
    "l": "",
    "m_date_of_event": "Sat, 17 - Sun, 18 Aug 2024",
    "n_event_name": "International Conference on Business Economics Social Science & Humanities (BESSH)",
    "o_description": "All Events in Singapore",
    "p": "",
    "q": "",
    "r": "",
    "s_state_province": "\n                    Grand Pacific Hotel,  SingaporeGet Directions",
    "t": "Singapore",
    "u": "Southeast Asia",
    "v": "",
    "w": "",
    "x": "",
    "y": "",
    "z": "",
    "aa": "",
    "ab_business_info": "Academic Fora",
    "ac_website": "",
    "ad": "",
    "ae": "",
    "af_country": "",
    "ag": "",
    "company_url": "https://10times.com/company/academic-fora"
  },
  {
    "a_date_farmed": "16/07/2024",
    "b_source": "10Times",
    "c_scraped_url": "https://10times.com/ecba-singapore",
    "d": "New Lead",
    "e": "Opportunity",
    "f": "Juan",
    "g": "Juan",
    "h": "Lara",
    "i": "Scraping",
    "j": "EDU Business",
    "k": "EDU Events",
    "l": "",
    "m_date_of_event": "Sat, 17 - Sun, 18 Aug 2024",
    "n_event_name": "International Conference on Engineering & Technology, Computer, Basic & Applied Sciences (ECBA)",
    "o_description": "All Events in Singapore",
    "p": "",
    "q": "",
    "r": "",
    "s_state_province": "\n                    Grand Pacific Hotel,  SingaporeGet Directions",
    "t": "Singapore",
    "u": "Southeast Asia",
    "v": "",
    "w": "",
    "x": "",
    "y": "",
    "z": "",
    "aa": "",
    "ab_business_info": "Academic Fora",
    "ac_website": "",
    "ad": "",
    "ae": "",
    "af_country": "",
    "ag": "",
    "company_url": "https://10times.com/company/academic-fora"
  },
  {
    "a_date_farmed": "16/07/2024",
    "b_source": "10Times",
    "c_scraped_url": "https://10times.com/iacebmss-singapore",
    "d": "New Lead",
    "e": "Opportunity",
    "f": "Juan",
    "g": "Juan",
    "h": "Lara",
    "i": "Scraping",
    "j": "EDU Business",
    "k": "EDU Events",
    "l": "",
    "m_date_of_event": "Sun, 11 - Mon, 12 Aug 2024",
    "n_event_name": "International Academic Conference on Economics, Business Management & Social Sciences (IACEBMSS)",
    "o_description": "All Events in Singapore",
    "p": "",
    "q": "",
    "r": "",
    "s_state_province": "Singapore",
    "t": "Singapore",
    "u": "Southeast Asia",
    "v": "",
    "w": "",
    "x": "",
    "y": "",
    "z": "",
    "aa": "",
    "ab_business_info": "Scienceglobe",
    "ac_website": "",
    "ad": "",
    "ae": "",
    "af_country": "",
    "ag": "",
    "company_url": "https://10times.com/company/scienceglobe"
  },
  {
    "a_date_farmed": "16/07/2024",
    "b_source": "10Times",
    "c_scraped_url": "https://10times.com/beauty-asia-singapore",
    "d": "New Lead",
    "e": "Opportunity",
    "f": "Juan",
    "g": "Juan",
    "h": "Lara",
    "i": "Scraping",
    "j": "EDU Business",
    "k": "EDU Events",
    "l": "",
    "m_date_of_event": "Mon, 17 - Wed, 19 Feb 2025",
    "n_event_name": "BeautyAsia - Singapore",
    "o_description": "",
    "p": "",
    "q": "",
    "r": "",
    "s_state_province": "",
    "t": "Singapore",
    "u": "Southeast Asia",
    "v": "",
    "w": "",
    "x": "",
    "y": "",
    "z": "",
    "aa": "",
    "ab_business_info": "",
    "ac_website": "",
    "ad": "",
    "ae": "",
    "af_country": "",
    "ag": "",
    "company_url": ""
  },
  {
    "a_date_farmed": "16/07/2024",
    "b_source": "10Times",
    "c_scraped_url": "https://10times.com/e1x2-4g2h-5xss",
    "d": "New Lead",
    "e": "Opportunity",
    "f": "Juan",
    "g": "Juan",
    "h": "Lara",
    "i": "Scraping",
    "j": "EDU Business",
    "k": "EDU Events",
    "l": "",
    "m_date_of_event": "Thu, 22 - Fri, 23 Aug 2024",
    "n_event_name": "International Conference on Language, Innovation, Culture and Education",
    "o_description": "All Events in Singapore",
    "p": "",
    "q": "",
    "r": "",
    "s_state_province": "Singapore",
    "t": "Singapore",
    "u": "Southeast Asia",
    "v": "",
    "w": "",
    "x": "",
    "y": "",
    "z": "",
    "aa": "",
    "ab_business_info": "E Conferences",
    "ac_website": "http://econf.co",
    "ad": "",
    "ae": "",
    "af_country": "UK",
    "ag": "",
    "company_url": "https://10times.com/company/econfco"
  },
  {
    "a_date_farmed": "16/07/2024",
    "b_source": "10Times",
    "c_scraped_url": "https://10times.com/shbc",
    "d": "New Lead",
    "e": "Opportunity",
    "f": "Juan",
    "g": "Juan",
    "h": "Lara",
    "i": "Scraping",
    "j": "EDU Business",
    "k": "EDU Events",
    "l": "",
    "m_date_of_event": "Thu, 10 - Fri, 11 Oct 2024",
    "n_event_name": "Singapore Health and Biomedical Congress (SHBC)",
    "o_description": "",
    "p": "",
    "q": "",
    "r": "",
    "s_state_province": "Singapore Expo, Singapore",
    "t": "Singapore",
    "u": "Southeast Asia",
    "v": "",
    "w": "",
    "x": "",
    "y": "",
    "z": "",
    "aa": "",
    "ab_business_info": "",
    "ac_website": "",
    "ad": "",
    "ae": "",
    "af_country": "",
    "ag": ""
  },
  {
    "a_date_farmed": "16/07/2024",
    "b_source": "10Times",
    "c_scraped_url": "https://10times.com/qs-connect-mba-singapore",
    "d": "New Lead",
    "e": "Opportunity",
    "f": "Juan",
    "g": "Juan",
    "h": "Lara",
    "i": "Scraping",
    "j": "EDU Business",
    "k": "EDU Events",
    "l": "",
    "m_date_of_event": "Sat, 17 Aug 2024",
    "n_event_name": "QS Connect MBA Singapore",
    "o_description": "",
    "p": "",
    "q": "",
    "r": "",
    "s_state_province": "",
    "t": "Singapore",
    "u": "Southeast Asia",
    "v": "",
    "w": "",
    "x": "",
    "y": "",
    "z": "",
    "aa": "",
    "ab_business_info": "",
    "ac_website": "",
    "ad": "",
    "ae": "",
    "af_country": "",
    "ag": "",
    "company_url": ""
  },
  {
    "a_date_farmed": "16/07/2024",
    "b_source": "10Times",
    "c_scraped_url": "",
    "d": "New Lead",
    "e": "Opportunity",
    "f": "Juan",
    "g": "Juan",
    "h": "Lara",
    "i": "Scraping",
    "j": "EDU Business",
    "k": "EDU Events",
    "l": "",
    "m_date_of_event": "",
    "n_event_name": "",
    "o_description": "",
    "p": "",
    "q": "",
    "r": "",
    "s_state_province": "",
    "t": "Singapore",
    "u": "Southeast Asia",
    "v": "",
    "w": "",
    "x": "",
    "y": "",
    "z": "",
    "aa": "",
    "ab_business_info": "",
    "ac_website": "",
    "ad": "",
    "ae": "",
    "af_country": "",
    "ag": ""
  },
  {
    "a_date_farmed": "16/07/2024",
    "b_source": "10Times",
    "c_scraped_url": "https://10times.com/icapm-singapore",
    "d": "New Lead",
    "e": "Opportunity",
    "f": "Juan",
    "g": "Juan",
    "h": "Lara",
    "i": "Scraping",
    "j": "EDU Business",
    "k": "EDU Events",
    "l": "",
    "m_date_of_event": "Tue, 20 - Wed, 21 Aug 2024",
    "n_event_name": "International Conference on Applied Physics and Mathematics (ICAPM)",
    "o_description": "International Conference on Applied Physics and Mathematics (ICAPM - 2024) aims to be a leading international conference for presenting novel advances in Social Science and Economics. Sponsored by IIER, it fosters communication among researchers and practitioners in various scientific areas.",
    "p": "",
    "q": "",
    "r": "",
    "s_state_province": "\n                    Arcc Spaces - 75 High Street,  SingaporeGet Directions",
    "t": "Singapore",
    "u": "Southeast Asia",
    "v": "",
    "w": "",
    "x": "",
    "y": "",
    "z": "",
    "aa": "",
    "ab_business_info": "International Institute of Engineers and Researchers (IIER)",
    "ac_website": "http://theiier.org",
    "ad": "",
    "ae": "",
    "af_country": "India",
    "ag": "",
    "company_url": "https://10times.com/company/international-institute-of-engineers-and-researchers-iier"
  },
  {
    "a_date_farmed": "16/07/2024",
    "b_source": "10Times",
    "c_scraped_url": "",
    "d": "New Lead",
    "e": "Opportunity",
    "f": "Juan",
    "g": "Juan",
    "h": "Lara",
    "i": "Scraping",
    "j": "EDU Business",
    "k": "EDU Events",
    "l": "",
    "m_date_of_event": "",
    "n_event_name": "",
    "o_description": "",
    "p": "",
    "q": "",
    "r": "",
    "s_state_province": "",
    "t": "Singapore",
    "u": "Southeast Asia",
    "v": "",
    "w": "",
    "x": "",
    "y": "",
    "z": "",
    "aa": "",
    "ab_business_info": "",
    "ac_website": "",
    "ad": "",
    "ae": "",
    "af_country": "",
    "ag": ""
  },
  {
    "a_date_farmed": "16/07/2024",
    "b_source": "10Times",
    "c_scraped_url": "https://10times.com/aetc",
    "d": "New Lead",
    "e": "Opportunity",
    "f": "Juan",
    "g": "Juan",
    "h": "Lara",
    "i": "Scraping",
    "j": "EDU Business",
    "k": "EDU Events",
    "l": "",
    "m_date_of_event": "Thu, 19 - Sat, 21 Sep 2024",
    "n_event_name": "The Asian Education Technology Conferenc",
    "o_description": "The Asian Education Technology Conference (AETC), organized by East Asia Research, will be held at the Holiday Inn Singapore Atrium. SETC is a conference for teacher educators and affiliated organizations interested in technology in education. Join us to share ideas and build connections in the field of learning technology.",
    "p": "",
    "q": "",
    "r": "",
    "s_state_province": "\n                    Holiday Inn Singapore Atrium,  SingaporeGet Directions",
    "t": "Singapore",
    "u": "Southeast Asia",
    "v": "",
    "w": "",
    "x": "",
    "y": "",
    "z": "",
    "aa": "",
    "ab_business_info": "",
    "ac_website": "",
    "ad": "",
    "ae": "",
    "af_country": "",
    "ag": "",
    "company_url": ""
  },
  {
    "a_date_farmed": "16/07/2024",
    "b_source": "10Times",
    "c_scraped_url": "",
    "d": "New Lead",
    "e": "Opportunity",
    "f": "Juan",
    "g": "Juan",
    "h": "Lara",
    "i": "Scraping",
    "j": "EDU Business",
    "k": "EDU Events",
    "l": "",
    "m_date_of_event": "",
    "n_event_name": "",
    "o_description": "",
    "p": "",
    "q": "",
    "r": "",
    "s_state_province": "",
    "t": "Singapore",
    "u": "Southeast Asia",
    "v": "",
    "w": "",
    "x": "",
    "y": "",
    "z": "",
    "aa": "",
    "ab_business_info": "",
    "ac_website": "",
    "ad": "",
    "ae": "",
    "af_country": "",
    "ag": ""
  },
  {
    "a_date_farmed": "16/07/2024",
    "b_source": "10Times",
    "c_scraped_url": "https://10times.com/singhealth-duke-nus-scientific-congress",
    "d": "New Lead",
    "e": "Opportunity",
    "f": "Juan",
    "g": "Juan",
    "h": "Lara",
    "i": "Scraping",
    "j": "EDU Business",
    "k": "EDU Events",
    "l": "",
    "m_date_of_event": "Fri, 27 - Sat, 28 Sep 2024",
    "n_event_name": "SingHealth Duke-NUS Education Congress",
    "o_description": "All Events in Singapore",
    "p": "",
    "q": "",
    "r": "",
    "s_state_province": "\n                    Academia,  SingaporeGet Directions",
    "t": "Singapore",
    "u": "Southeast Asia",
    "v": "",
    "w": "",
    "x": "",
    "y": "",
    "z": "",
    "aa": "",
    "ab_business_info": "SingHealth Academy",
    "ac_website": "",
    "ad": "",
    "ae": "",
    "af_country": "",
    "ag": "",
    "company_url": "https://10times.com/company/singhealth-academy"
  },
  {
    "a_date_farmed": "16/07/2024",
    "b_source": "10Times",
    "c_scraped_url": "https://10times.com/singapore-forex-expo",
    "d": "New Lead",
    "e": "Opportunity",
    "f": "Juan",
    "g": "Juan",
    "h": "Lara",
    "i": "Scraping",
    "j": "EDU Business",
    "k": "EDU Events",
    "l": "",
    "m_date_of_event": "Sat, 08 Mar 2025",
    "n_event_name": "Traders Fair Singapore",
    "o_description": "\"Fantastic shows like nowhere!\"Traders Fair offers dynamic financial events across Asia and beyond, providing educational seminars, networking opportunities, and interactive workshops with industry experts. Created by FINEXPO, Traders Fair aims to connect traders, investors, and financial advisors worldwide, offering a unique blend of education and innovation in the trading industry.",
    "p": "",
    "q": "",
    "r": "",
    "s_state_province": "\n                    Sands Expo and Convention Centre,  SingaporeGet Directions",
    "t": "Singapore",
    "u": "Southeast Asia",
    "v": "",
    "w": "",
    "x": "",
    "y": "",
    "z": "",
    "aa": "",
    "ab_business_info": "FINEXPO",
    "ac_website": "",
    "ad": "",
    "ae": "",
    "af_country": "",
    "ag": "",
    "company_url": "https://10times.com/company/finexpo"
  },
  {
    "a_date_farmed": "16/07/2024",
    "b_source": "10Times",
    "c_scraped_url": "https://10times.com/cash-flow-training-singapore",
    "d": "New Lead",
    "e": "Opportunity",
    "f": "Juan",
    "g": "Juan",
    "h": "Lara",
    "i": "Scraping",
    "j": "EDU Business",
    "k": "EDU Events",
    "l": "",
    "m_date_of_event": "Thu, 19 - Fri, 20 Sep 2024",
    "n_event_name": "Cash Flow and Working Capital Management Training",
    "o_description": "Build your career with our industry-related courses. The Course will provide participants with a structured process to analyze cash and working capital information, improve analytical skills, and make better business decisions. Interactive discussions, case studies, and practical examples included.",
    "p": "",
    "q": "",
    "r": "",
    "s_state_province": "Singapore",
    "t": "Singapore",
    "u": "Southeast Asia",
    "v": "",
    "w": "",
    "x": "",
    "y": "",
    "z": "",
    "aa": "",
    "ab_business_info": "Riverstone Training",
    "ac_website": "http://www.riverstonetraining.com.sg/",
    "ad": "",
    "ae": "",
    "af_country": "",
    "ag": "",
    "company_url": "https://10times.com/company/riverstone-training"
  },
  {
    "a_date_farmed": "16/07/2024",
    "b_source": "10Times",
    "c_scraped_url": "https://10times.com/e1d0-h6f0-p3df-h",
    "d": "New Lead",
    "e": "Opportunity",
    "f": "Juan",
    "g": "Juan",
    "h": "Lara",
    "i": "Scraping",
    "j": "EDU Business",
    "k": "EDU Events",
    "l": "",
    "m_date_of_event": "Mon, 05 - Wed, 07 Aug 2024",
    "n_event_name": "Credit Research Foundation Expo",
    "o_description": "Join us for a valuable Forum PLUS a special two-night celebration for our 75th Anniversary! The Credit Research Foundation is excited to host this in-person Forum and EXPO offering educational sessions curated by industry experts, several opportunities for peer group networking, and dedicated time in the exhibit hall.",
    "p": "",
    "q": "",
    "r": "",
    "s_state_province": "\n                    The Fullerton Hotel Singapore,  SingaporeGet Directions",
    "t": "Singapore",
    "u": "Southeast Asia",
    "v": "",
    "w": "",
    "x": "",
    "y": "",
    "z": "",
    "aa": "",
    "ab_business_info": "",
    "ac_website": "",
    "ad": "",
    "ae": "",
    "af_country": "",
    "ag": "",
    "company_url": ""
  },
  {
    "a_date_farmed": "16/07/2024",
    "b_source": "10Times",
    "c_scraped_url": "https://10times.com/icrdssbm-singapore",
    "d": "New Lead",
    "e": "Opportunity",
    "f": "Juan",
    "g": "Juan",
    "h": "Lara",
    "i": "Scraping",
    "j": "EDU Business",
    "k": "EDU Events",
    "l": "",
    "m_date_of_event": "Tue, 06 Aug 2024",
    "n_event_name": "International Conference on Recent Developments in Social Science and Business Management (ICRDSSBM)",
    "o_description": "",
    "p": "",
    "q": "",
    "r": "",
    "s_state_province": "",
    "t": "Singapore",
    "u": "Southeast Asia",
    "v": "",
    "w": "",
    "x": "",
    "y": "",
    "z": "",
    "aa": "",
    "ab_business_info": "",
    "ac_website": "",
    "ad": "",
    "ae": "",
    "af_country": "",
    "ag": "",
    "company_url": ""
  },
  {
    "a_date_farmed": "16/07/2024",
    "b_source": "10Times",
    "c_scraped_url": "https://10times.com/mlv",
    "d": "New Lead",
    "e": "Opportunity",
    "f": "Juan",
    "g": "Juan",
    "h": "Lara",
    "i": "Scraping",
    "j": "EDU Business",
    "k": "EDU Events",
    "l": "",
    "m_date_of_event": "Thu, 26 - Fri, 27 Sep 2024",
    "n_event_name": "The Art of Making Childrens Learning Visible",
    "o_description": "\"Professional Development for Teachers\"Pedagogical documentation is a fundamental working tool and strategy for teachers, seeking to make visible and understand what takes place during pedagogical work, how much, and what, children know and can do. The crux of documentation is to make the learning and teaching process visible. In other words, it highlights how the children planned, carried out, and completed their work and the subtle way teachers facilitated learning. This workshop aims to increase participants' knowledge, skill and confidence level in documenting and using documentation to improve the learning and teaching process.",
    "p": "",
    "q": "",
    "r": "",
    "s_state_province": "Singapore  •  Virtual Event",
    "t": "Singapore",
    "u": "Southeast Asia",
    "v": "",
    "w": "",
    "x": "",
    "y": "",
    "z": "",
    "aa": "",
    "ab_business_info": "Sanguine Consulting",
    "ac_website": "",
    "ad": "",
    "ae": "",
    "af_country": "",
    "ag": "",
    "company_url": "https://10times.com/company/sanguine-consultancy"
  },
  {
    "a_date_farmed": "16/07/2024",
    "b_source": "10Times",
    "c_scraped_url": "https://10times.com/leadership-summit-singapore",
    "d": "New Lead",
    "e": "Opportunity",
    "f": "Juan",
    "g": "Juan",
    "h": "Lara",
    "i": "Scraping",
    "j": "EDU Business",
    "k": "EDU Events",
    "l": "",
    "m_date_of_event": "Wed, 30 - Thu, 31 Oct 2024",
    "n_event_name": "The Global Leadership Summit (GLS)",
    "o_description": "The Global Leadership Summit exists to transform Christian leaders around the world with an injection of vision, skill development, and inspiration for the empowerment of the church and kingdom impact.",
    "p": "",
    "q": "",
    "r": "",
    "s_state_province": "\n                    Bethesda (Bedok-Tampines) Church,  SingaporeGet Directions",
    "t": "Singapore",
    "u": "Southeast Asia",
    "v": "",
    "w": "",
    "x": "",
    "y": "",
    "z": "",
    "aa": "",
    "ab_business_info": "Global Leadership Network",
    "ac_website": "",
    "ad": "",
    "ae": "",
    "af_country": "",
    "ag": "",
    "company_url": "https://10times.com/company/willow-creek-association"
  },
  {
    "a_date_farmed": "16/07/2024",
    "b_source": "10Times",
    "c_scraped_url": "https://10times.com/icesd-singapore",
    "d": "New Lead",
    "e": "Opportunity",
    "f": "Juan",
    "g": "Juan",
    "h": "Lara",
    "i": "Scraping",
    "j": "EDU Business",
    "k": "EDU Events",
    "l": "",
    "m_date_of_event": "Mon, 02 - Tue, 03 Sep 2024",
    "n_event_name": "International Conference on Environmental Science and Development (ICESD)",
    "o_description": "",
    "p": "",
    "q": "",
    "r": "",
    "s_state_province": "",
    "t": "Singapore",
    "u": "Southeast Asia",
    "v": "",
    "w": "",
    "x": "",
    "y": "",
    "z": "",
    "aa": "",
    "ab_business_info": "",
    "ac_website": "",
    "ad": "",
    "ae": "",
    "af_country": "",
    "ag": "",
    "company_url": ""
  },
  {
    "a_date_farmed": "16/07/2024",
    "b_source": "10Times",
    "c_scraped_url": "https://10times.com/icmr-singapore",
    "d": "New Lead",
    "e": "Opportunity",
    "f": "Juan",
    "g": "Juan",
    "h": "Lara",
    "i": "Scraping",
    "j": "EDU Business",
    "k": "EDU Events",
    "l": "",
    "m_date_of_event": "Fri, 19 Jul 2024",
    "n_event_name": "International Conference on Multidisciplinary Research (ICMR)",
    "o_description": "ICMR 2024 provides a platform for global participants to share ideas, establish collaborations, and contribute to scientific knowledge. Sponsored by SAARD, the conference features invited lectures, paper awards, and publication opportunities. Past conferences were held in various international locations.",
    "p": "",
    "q": "",
    "r": "",
    "s_state_province": "\n                    Village Hotel Changi,  SingaporeGet Directions",
    "t": "Singapore",
    "u": "Southeast Asia",
    "v": "",
    "w": "",
    "x": "",
    "y": "",
    "z": "",
    "aa": "",
    "ab_business_info": "",
    "ac_website": "",
    "ad": "",
    "ae": "",
    "af_country": "",
    "ag": "",
    "company_url": ""
  },
  {
    "a_date_farmed": "16/07/2024",
    "b_source": "10Times",
    "c_scraped_url": "https://10times.com/esmo-singapore",
    "d": "New Lead",
    "e": "Opportunity",
    "f": "Juan",
    "g": "Juan",
    "h": "Lara",
    "i": "Scraping",
    "j": "EDU Business",
    "k": "EDU Events",
    "l": "",
    "m_date_of_event": "Fri, 06 - Sun, 08 Dec 2024",
    "n_event_name": "ESMO Asia Congress",
    "o_description": "",
    "p": "",
    "q": "",
    "r": "",
    "s_state_province": "",
    "t": "Singapore",
    "u": "Southeast Asia",
    "v": "",
    "w": "",
    "x": "",
    "y": "",
    "z": "",
    "aa": "",
    "ab_business_info": "",
    "ac_website": "",
    "ad": "",
    "ae": "",
    "af_country": "",
    "ag": "",
    "company_url": ""
  },
  {
    "a_date_farmed": "16/07/2024",
    "b_source": "10Times",
    "c_scraped_url": "",
    "d": "New Lead",
    "e": "Opportunity",
    "f": "Juan",
    "g": "Juan",
    "h": "Lara",
    "i": "Scraping",
    "j": "EDU Business",
    "k": "EDU Events",
    "l": "",
    "m_date_of_event": "",
    "n_event_name": "",
    "o_description": "",
    "p": "",
    "q": "",
    "r": "",
    "s_state_province": "",
    "t": "Singapore",
    "u": "Southeast Asia",
    "v": "",
    "w": "",
    "x": "",
    "y": "",
    "z": "",
    "aa": "",
    "ab_business_info": "",
    "ac_website": "",
    "ad": "",
    "ae": "",
    "af_country": "",
    "ag": ""
  },
  {
    "a_date_farmed": "16/07/2024",
    "b_source": "10Times",
    "c_scraped_url": "https://10times.com/ichssbm-singapore",
    "d": "New Lead",
    "e": "Opportunity",
    "f": "Juan",
    "g": "Juan",
    "h": "Lara",
    "i": "Scraping",
    "j": "EDU Business",
    "k": "EDU Events",
    "l": "",
    "m_date_of_event": "Sun, 21 - Mon, 22 Jul 2024",
    "n_event_name": "International Conference on Humanities, Social Science and Business Management (ICHSSBM)",
    "o_description": "All Events in Singapore",
    "p": "",
    "q": "",
    "r": "",
    "s_state_province": "\n                    Village Hotel Changi,  SingaporeGet Directions",
    "t": "Singapore",
    "u": "Southeast Asia",
    "v": "",
    "w": "",
    "x": "",
    "y": "",
    "z": "",
    "aa": "",
    "ab_business_info": "",
    "ac_website": "",
    "ad": "",
    "ae": "",
    "af_country": "",
    "ag": "",
    "company_url": ""
  },
  {
    "a_date_farmed": "16/07/2024",
    "b_source": "10Times",
    "c_scraped_url": "https://10times.com/e1x4-721z-zfgz",
    "d": "New Lead",
    "e": "Opportunity",
    "f": "Juan",
    "g": "Juan",
    "h": "Lara",
    "i": "Scraping",
    "j": "EDU Business",
    "k": "EDU Events",
    "l": "",
    "m_date_of_event": "Thu, 01 - Fri, 02 Aug 2024",
    "n_event_name": "Preventing and Addressing Challenging Behaviors in Young Children (Challenging Behavior)",
    "o_description": "\"Register Now!\"Challenging behaviors have been identified as a primary concern facing public schools and families (Fox & Hemmeter, 2009). Studies have documented that persistent challenging behaviors are directly associated with poor social and academic outcomes (Frey et al., 2015; McClelland et al., 2006). The importance of addressing challenging behaviors and promoting social development in the early years is well documented and clear links exist between early emotional development and later social behavior (Jones et al., 2015).",
    "p": "",
    "q": "",
    "r": "",
    "s_state_province": "\n                    to be advised, \t\t\t\t\t\t\t\t\t\t\tSingaporeGet Directions",
    "t": "Singapore",
    "u": "Southeast Asia",
    "v": "",
    "w": "",
    "x": "",
    "y": "",
    "z": "",
    "aa": "",
    "ab_business_info": "Sanguine Consulting",
    "ac_website": "",
    "ad": "",
    "ae": "",
    "af_country": "",
    "ag": "",
    "company_url": "https://10times.com/company/sanguine-consultancy"
  },
  {
    "a_date_farmed": "16/07/2024",
    "b_source": "10Times",
    "c_scraped_url": "https://10times.com/idmc-singapore",
    "d": "New Lead",
    "e": "Opportunity",
    "f": "Juan",
    "g": "Juan",
    "h": "Lara",
    "i": "Scraping",
    "j": "EDU Business",
    "k": "EDU Events",
    "l": "",
    "m_date_of_event": "Fri, 30 - Sat, 31 Aug 2024",
    "n_event_name": "IDMC Singapore",
    "o_description": "",
    "p": "",
    "q": "",
    "r": "",
    "s_state_province": "",
    "t": "Singapore",
    "u": "Southeast Asia",
    "v": "",
    "w": "",
    "x": "",
    "y": "",
    "z": "",
    "aa": "",
    "ab_business_info": "",
    "ac_website": "",
    "ad": "",
    "ae": "",
    "af_country": "",
    "ag": "",
    "company_url": ""
  },
  {
    "a_date_farmed": "16/07/2024",
    "b_source": "10Times",
    "c_scraped_url": "https://10times.com/fund-raising-training-singapore",
    "d": "New Lead",
    "e": "Opportunity",
    "f": "Juan",
    "g": "Juan",
    "h": "Lara",
    "i": "Scraping",
    "j": "EDU Business",
    "k": "EDU Events",
    "l": "",
    "m_date_of_event": "Mon, 05 - Wed, 07 Aug 2024",
    "n_event_name": "Startups Valuation and Fund Raising (SVF)",
    "o_description": "",
    "p": "",
    "q": "",
    "r": "",
    "s_state_province": "",
    "t": "Singapore",
    "u": "Southeast Asia",
    "v": "",
    "w": "",
    "x": "",
    "y": "",
    "z": "",
    "aa": "",
    "ab_business_info": "",
    "ac_website": "",
    "ad": "",
    "ae": "",
    "af_country": "",
    "ag": "",
    "company_url": ""
  },
  {
    "a_date_farmed": "16/07/2024",
    "b_source": "10Times",
    "c_scraped_url": "https://10times.com/wit-singapore",
    "d": "New Lead",
    "e": "Opportunity",
    "f": "Juan",
    "g": "Juan",
    "h": "Lara",
    "i": "Scraping",
    "j": "EDU Business",
    "k": "EDU Events",
    "l": "",
    "m_date_of_event": "Mon, 14 - Wed, 16 Oct 2024",
    "n_event_name": "WIT Singapore Conference",
    "o_description": "All Events in Singapore",
    "p": "",
    "q": "",
    "r": "",
    "s_state_province": "\n                    Sands Expo and Convention Centre,  SingaporeGet Directions",
    "t": "Singapore",
    "u": "Southeast Asia",
    "v": "",
    "w": "",
    "x": "",
    "y": "",
    "z": "",
    "aa": "",
    "ab_business_info": "Northstar Travel Media LLC",
    "ac_website": "https://www.northstartravelgroup.com/",
    "ad": "",
    "ae": "",
    "af_country": "USA",
    "ag": "",
    "company_url": "https://10times.com/company/northstar-travel-mediallc"
  },
  {
    "a_date_farmed": "16/07/2024",
    "b_source": "10Times",
    "c_scraped_url": "https://10times.com/e1x2-05h9-rfxp",
    "d": "New Lead",
    "e": "Opportunity",
    "f": "Juan",
    "g": "Juan",
    "h": "Lara",
    "i": "Scraping",
    "j": "EDU Business",
    "k": "EDU Events",
    "l": "",
    "m_date_of_event": "Wed, 24 - Thu, 25 Jul 2024",
    "n_event_name": "Minitab Software Training and Certification",
    "o_description": "All Events in Singapore",
    "p": "",
    "q": "",
    "r": "",
    "s_state_province": "Singapore",
    "t": "Singapore",
    "u": "Southeast Asia",
    "v": "",
    "w": "",
    "x": "",
    "y": "",
    "z": "",
    "aa": "",
    "ab_business_info": "",
    "ac_website": "",
    "ad": "",
    "ae": "",
    "af_country": "",
    "ag": "",
    "company_url": ""
  },
  {
    "a_date_farmed": "16/07/2024",
    "b_source": "10Times",
    "c_scraped_url": "https://10times.com/e10d-hdsp-3x2z-0",
    "d": "New Lead",
    "e": "Opportunity",
    "f": "Juan",
    "g": "Juan",
    "h": "Lara",
    "i": "Scraping",
    "j": "EDU Business",
    "k": "EDU Events",
    "l": "",
    "m_date_of_event": "Tue, 27 - Thu, 29 Aug 2024",
    "n_event_name": "MLPRAE01 '24: The International Conference on Machine Learning, Pattern Recognition, and Automation Engineering...",
    "o_description": "ACM is the world's largest educational and scientific computing society, offering resources to advance computing as a science and profession. It provides a premier Digital Library and supports members with publications, conferences, and career resources.",
    "p": "",
    "q": "",
    "r": "",
    "s_state_province": "Singapore",
    "t": "Singapore",
    "u": "Southeast Asia",
    "v": "",
    "w": "",
    "x": "",
    "y": "",
    "z": "",
    "aa": "",
    "ab_business_info": "",
    "ac_website": "",
    "ad": "",
    "ae": "",
    "af_country": "",
    "ag": "",
    "company_url": ""
  },
  {
    "a_date_farmed": "16/07/2024",
    "b_source": "10Times",
    "c_scraped_url": "",
    "d": "New Lead",
    "e": "Opportunity",
    "f": "Juan",
    "g": "Juan",
    "h": "Lara",
    "i": "Scraping",
    "j": "EDU Business",
    "k": "EDU Events",
    "l": "",
    "m_date_of_event": "",
    "n_event_name": "",
    "o_description": "",
    "p": "",
    "q": "",
    "r": "",
    "s_state_province": "",
    "t": "Singapore",
    "u": "Southeast Asia",
    "v": "",
    "w": "",
    "x": "",
    "y": "",
    "z": "",
    "aa": "",
    "ab_business_info": "",
    "ac_website": "",
    "ad": "",
    "ae": "",
    "af_country": "",
    "ag": ""
  }
]